orange/__init__.py
orange/__main__.py
orange/dashboard.py
orange/utils.py
Omodem-1.5.0.dist-info/METADATA
Omodem-1.5.0.dist-info/WHEEL
Omodem-1.5.0.dist-info/entry_points.txt
Omodem-1.5.0.dist-info/top_level.txt
Omodem-1.5.0.dist-info/RECORD
