Metadata-Version: 2.1
Name: Omodem
Version: 1.5.0
Summary: A tui app to manage a orange modem !
Author: Pinokaille
License: MIT
Requires-Dist: bs4
Requires-Dist: requests
